opentelemetry/instrumentation/valkey/__init__.py
opentelemetry/instrumentation/valkey/custom_types.py
opentelemetry/instrumentation/valkey/package.py
opentelemetry/instrumentation/valkey/py.typed
opentelemetry/instrumentation/valkey/util.py
opentelemetry/instrumentation/valkey/version.py
opentelemetry_python_contrib_external_valkey-0.60b1.dist-info/licenses/LICENSE
opentelemetry_python_contrib_external_valkey-0.60b1.dist-info/WHEEL
opentelemetry_python_contrib_external_valkey-0.60b1.dist-info/entry_points.txt
opentelemetry_python_contrib_external_valkey-0.60b1.dist-info/METADATA
opentelemetry_python_contrib_external_valkey-0.60b1.dist-info/RECORD
